{
  "investor_id": "buffett",
  "cik": "0001067983",
  "quarter": "2026-Q1",
  "report_date": "2026-03-31",
  "filing_date": "2026-05-15",
  "accession_number": "0001193125-26-226661",
  "total_value": 263095703570,
  "num_holdings": 90,
  "holdings": [
    {
      "cusip": "02005N100",
      "name": "ALLY FINL INC",
      "ticker": "ALLY",
      "title_of_class": "COM",
      "value": 498992850,
      "shares": 12719675,
      "share_type": "SH",
      "put_call": null,
      "sector": null
    },
    {
      "cusip": "02005N100",
      "name": "ALLY FINL INC",
      "ticker": "ALLY",
      "title_of_class": "COM",
      "value": 109996016,
      "shares": 2803875,
      "share_type": "SH",
      "put_call": null,
      "sector": null
    },
    {
      "cusip": "02005N100",
      "name": "ALLY FINL INC",
      "ticker": "ALLY",
      "title_of_class": "COM",
      "value": 165872286,
      "shares": 4228200,
      "share_type": "SH",
      "put_call": null,
      "sector": null
    },
    {
      "cusip": "02005N100",
      "name": "ALLY FINL INC",
      "ticker": "ALLY",
      "title_of_class": "COM",
      "value": 123064510,
      "shares": 3137000,
      "share_type": "SH",
      "put_call": null,
      "sector": null
    },
    {
      "cusip": "02005N100",
      "name": "ALLY FINL INC",
      "ticker": "ALLY",
      "title_of_class": "COM",
      "value": 189726088,
      "shares": 4836250,
      "share_type": "SH",
      "put_call": null,
      "sector": null
    },
    {
      "cusip": "02005N100",
      "name": "ALLY FINL INC",
      "ticker": "ALLY",
      "title_of_class": "COM",
      "value": 50018250,
      "shares": 1275000,
      "share_type": "SH",
      "put_call": null,
      "sector": null
    },
    {
      "cusip": "02079K107",
      "name": "ALPHABET INC",
      "ticker": "GOOG",
      "title_of_class": "CAP STK CL C",
      "value": 1028454775,
      "shares": 3585215,
      "share_type": "SH",
      "put_call": null,
      "sector": null
    },
    {
      "cusip": "02079K305",
      "name": "ALPHABET INC",
      "ticker": "GOOG",
      "title_of_class": "CAP STK CL A",
      "value": 4802252,
      "shares": 16700,
      "share_type": "SH",
      "put_call": null,
      "sector": null
    },
    {
      "cusip": "02079K305",
      "name": "ALPHABET INC",
      "ticker": "GOOG",
      "title_of_class": "CAP STK CL A",
      "value": 1926652000,
      "shares": 6700000,
      "share_type": "SH",
      "put_call": null,
      "sector": null
    },
    {
      "cusip": "02079K305",
      "name": "ALPHABET INC",
      "ticker": "GOOG",
      "title_of_class": "CAP STK CL A",
      "value": 1797250000,
      "shares": 6250000,
      "share_type": "SH",
      "put_call": null,
      "sector": null
    },
    {
      "cusip": "02079K305",
      "name": "ALPHABET INC",
      "ticker": "GOOG",
      "title_of_class": "CAP STK CL A",
      "value": 11871367661,
      "shares": 41283098,
      "share_type": "SH",
      "put_call": null,
      "sector": null
    },
    {
      "cusip": "025816109",
      "name": "AMERICAN EXPRESS CO",
      "ticker": "AXP",
      "title_of_class": "COM",
      "value": 347834456,
      "shares": 1149942,
      "share_type": "SH",
      "put_call": null,
      "sector": null
    },
    {
      "cusip": "025816109",
      "name": "AMERICAN EXPRESS CO",
      "ticker": "AXP",
      "title_of_class": "COM",
      "value": 45087984892,
      "shares": 149061045,
      "share_type": "SH",
      "put_call": null,
      "sector": null
    },
    {
      "cusip": "025816109",
      "name": "AMERICAN EXPRESS CO",
      "ticker": "AXP",
      "title_of_class": "COM",
      "value": 423385188,
      "shares": 1399713,
      "share_type": "SH",
      "put_call": null,
      "sector": null
    },
    {
      "cusip": "037833100",
      "name": "APPLE INC",
      "ticker": "AAPL",
      "title_of_class": "COM",
      "value": 175622680,
      "shares": 692000,
      "share_type": "SH",
      "put_call": null,
      "sector": null
    },
    {
      "cusip": "037833100",
      "name": "APPLE INC",
      "ticker": "AAPL",
      "title_of_class": "COM",
      "value": 974553600,
      "shares": 3840000,
      "share_type": "SH",
      "put_call": null,
      "sector": null
    },
    {
      "cusip": "037833100",
      "name": "APPLE INC",
      "ticker": "AAPL",
      "title_of_class": "COM",
      "value": 8628860,
      "shares": 34000,
      "share_type": "SH",
      "put_call": null,
      "sector": null
    },
    {
      "cusip": "037833100",
      "name": "APPLE INC",
      "ticker": "AAPL",
      "title_of_class": "COM",
      "value": 8812603960,
      "shares": 34724000,
      "share_type": "SH",
      "put_call": null,
      "sector": null
    },
    {
      "cusip": "037833100",
      "name": "APPLE INC",
      "ticker": "AAPL",
      "title_of_class": "COM",
      "value": 691323960,
      "shares": 2724000,
      "share_type": "SH",
      "put_call": null,
      "sector": null
    },
    {
      "cusip": "037833100",
      "name": "APPLE INC",
      "ticker": "AAPL",
      "title_of_class": "COM",
      "value": 3941866280,
      "shares": 15532000,
      "share_type": "SH",
      "put_call": null,
      "sector": null
    },
    {
      "cusip": "037833100",
      "name": "APPLE INC",
      "ticker": "AAPL",
      "title_of_class": "COM",
      "value": 15618994925,
      "shares": 61542988,
      "share_type": "SH",
      "put_call": null,
      "sector": null
    },
    {
      "cusip": "037833100",
      "name": "APPLE INC",
      "ticker": "AAPL",
      "title_of_class": "COM",
      "value": 1828303160,
      "shares": 7204000,
      "share_type": "SH",
      "put_call": null,
      "sector": null
    },
    {
      "cusip": "037833100",
      "name": "APPLE INC",
      "ticker": "AAPL",
      "title_of_class": "COM",
      "value": 3672848880,
      "shares": 14472000,
      "share_type": "SH",
      "put_call": null,
      "sector": null
    },
    {
      "cusip": "037833100",
      "name": "APPLE INC",
      "ticker": "AAPL",
      "title_of_class": "COM",
      "value": 20471924668,
      "shares": 80664820,
      "share_type": "SH",
      "put_call": null,
      "sector": null
    },
    {
      "cusip": "037833100",
      "name": "APPLE INC",
      "ticker": "AAPL",
      "title_of_class": "COM",
      "value": 688278480,
      "shares": 2712000,
      "share_type": "SH",
      "put_call": null,
      "sector": null
    },
    {
      "cusip": "037833100",
      "name": "APPLE INC",
      "ticker": "AAPL",
      "title_of_class": "COM",
      "value": 958311040,
      "shares": 3776000,
      "share_type": "SH",
      "put_call": null,
      "sector": null
    },
    {
      "cusip": "060505104",
      "name": "BANK AMERICA CORP",
      "ticker": "UNKNOWN",
      "title_of_class": "COM",
      "value": 191100000,
      "shares": 3920000,
      "share_type": "SH",
      "put_call": null,
      "sector": null
    },
    {
      "cusip": "060505104",
      "name": "BANK AMERICA CORP",
      "ticker": "UNKNOWN",
      "title_of_class": "COM",
      "value": 580125000,
      "shares": 11900000,
      "share_type": "SH",
      "put_call": null,
      "sector": null
    },
    {
      "cusip": "060505104",
      "name": "BANK AMERICA CORP",
      "ticker": "UNKNOWN",
      "title_of_class": "COM",
      "value": 7093125,
      "shares": 145500,
      "share_type": "SH",
      "put_call": null,
      "sector": null
    },
    {
      "cusip": "060505104",
      "name": "BANK AMERICA CORP",
      "ticker": "UNKNOWN",
      "title_of_class": "COM",
      "value": 1376634919,
      "shares": 28238665,
      "share_type": "SH",
      "put_call": null,
      "sector": null
    },
    {
      "cusip": "060505104",
      "name": "BANK AMERICA CORP",
      "ticker": "UNKNOWN",
      "title_of_class": "COM",
      "value": 102375000,
      "shares": 2100000,
      "share_type": "SH",
      "put_call": null,
      "sector": null
    },
    {
      "cusip": "060505104",
      "name": "BANK AMERICA CORP",
      "ticker": "UNKNOWN",
      "title_of_class": "COM",
      "value": 1023750000,
      "shares": 21000000,
      "share_type": "SH",
      "put_call": null,
      "sector": null
    },
    {
      "cusip": "060505104",
      "name": "BANK AMERICA CORP",
      "ticker": "UNKNOWN",
      "title_of_class": "COM",
      "value": 15151500000,
      "shares": 310800000,
      "share_type": "SH",
      "put_call": null,
      "sector": null
    },
    {
      "cusip": "060505104",
      "name": "BANK AMERICA CORP",
      "ticker": "UNKNOWN",
      "title_of_class": "COM",
      "value": 6128850000,
      "shares": 125720000,
      "share_type": "SH",
      "put_call": null,
      "sector": null
    },
    {
      "cusip": "060505104",
      "name": "BANK AMERICA CORP",
      "ticker": "UNKNOWN",
      "title_of_class": "COM",
      "value": 477750000,
      "shares": 9800000,
      "share_type": "SH",
      "put_call": null,
      "sector": null
    },
    {
      "cusip": "14040H105",
      "name": "CAPITAL ONE FINL CORP",
      "ticker": "COF-PN",
      "title_of_class": "COM",
      "value": 353770628,
      "shares": 1939213,
      "share_type": "SH",
      "put_call": null,
      "sector": null
    },
    {
      "cusip": "14040H105",
      "name": "CAPITAL ONE FINL CORP",
      "ticker": "COF-PN",
      "title_of_class": "COM",
      "value": 560750962,
      "shares": 3073787,
      "share_type": "SH",
      "put_call": null,
      "sector": null
    },
    {
      "cusip": "14040H105",
      "name": "CAPITAL ONE FINL CORP",
      "ticker": "COF-PN",
      "title_of_class": "COM",
      "value": 389852910,
      "shares": 2137000,
      "share_type": "SH",
      "put_call": null,
      "sector": null
    },
    {
      "cusip": "166764100",
      "name": "CHEVRON CORPORATION",
      "ticker": "CVX",
      "title_of_class": "COM",
      "value": 714685980,
      "shares": 3454258,
      "share_type": "SH",
      "put_call": null,
      "sector": null
    },
    {
      "cusip": "166764100",
      "name": "CHEVRON CORPORATION",
      "ticker": "CVX",
      "title_of_class": "COM",
      "value": 1901860180,
      "shares": 9192171,
      "share_type": "SH",
      "put_call": null,
      "sector": null
    },
    {
      "cusip": "166764100",
      "name": "CHEVRON CORPORATION",
      "ticker": "CVX",
      "title_of_class": "COM",
      "value": 2788531578,
      "shares": 13477678,
      "share_type": "SH",
      "put_call": null,
      "sector": null
    },
    {
      "cusip": "166764100",
      "name": "CHEVRON CORPORATION",
      "ticker": "CVX",
      "title_of_class": "COM",
      "value": 12052286868,
      "shares": 58251749,
      "share_type": "SH",
      "put_call": null,
      "sector": null
    },
    {
      "cusip": "191216100",
      "name": "COCA COLA CO",
      "ticker": "KO",
      "title_of_class": "COM",
      "value": 60840000,
      "shares": 800000,
      "share_type": "SH",
      "put_call": null,
      "sector": null
    },
    {
      "cusip": "191216100",
      "name": "COCA COLA CO",
      "ticker": "KO",
      "title_of_class": "COM",
      "value": 28250370,
      "shares": 371471,
      "share_type": "SH",
      "put_call": null,
      "sector": null
    },
    {
      "cusip": "191216100",
      "name": "COCA COLA CO",
      "ticker": "KO",
      "title_of_class": "COM",
      "value": 6464250,
      "shares": 85000,
      "share_type": "SH",
      "put_call": null,
      "sector": null
    },
    {
      "cusip": "191216100",
      "name": "COCA COLA CO",
      "ticker": "KO",
      "title_of_class": "COM",
      "value": 6105537360,
      "shares": 80283200,
      "share_type": "SH",
      "put_call": null,
      "sector": null
    },
    {
      "cusip": "191216100",
      "name": "COCA COLA CO",
      "ticker": "KO",
      "title_of_class": "COM",
      "value": 138715200,
      "shares": 1824000,
      "share_type": "SH",
      "put_call": null,
      "sector": null
    },
    {
      "cusip": "191216100",
      "name": "COCA COLA CO",
      "ticker": "KO",
      "title_of_class": "COM",
      "value": 1095971760,
      "shares": 14411200,
      "share_type": "SH",
      "put_call": null,
      "sector": null
    },
    {
      "cusip": "191216100",
      "name": "COCA COLA CO",
      "ticker": "KO",
      "title_of_class": "COM",
      "value": 1140019920,
      "shares": 14990400,
      "share_type": "SH",
      "put_call": null,
      "sector": null
    },
    {
      "cusip": "191216100",
      "name": "COCA COLA CO",
      "ticker": "KO",
      "title_of_class": "COM",
      "value": 21501063540,
      "shares": 282722729,
      "share_type": "SH",
      "put_call": null,
      "sector": null
    },
    {
      "cusip": "191216100",
      "name": "COCA COLA CO",
      "ticker": "KO",
      "title_of_class": "COM",
      "value": 270129600,
      "shares": 3552000,
      "share_type": "SH",
      "put_call": null,
      "sector": null
    },
    {
      "cusip": "191216100",
      "name": "COCA COLA CO",
      "ticker": "KO",
      "title_of_class": "COM",
      "value": 73008000,
      "shares": 960000,
      "share_type": "SH",
      "put_call": null,
      "sector": null
    },
    {
      "cusip": "21036P108",
      "name": "CONSTELLATION BRANDS INC",
      "ticker": "STZ",
      "title_of_class": "CL A",
      "value": 94933500,
      "shares": 632890,
      "share_type": "SH",
      "put_call": null,
      "sector": null
    },
    {
      "cusip": "23918K108",
      "name": "DAVITA INC",
      "ticker": "DVA",
      "title_of_class": "COM",
      "value": 2301293814,
      "shares": 14973608,
      "share_type": "SH",
      "put_call": null,
      "sector": null
    },
    {
      "cusip": "23918K108",
      "name": "DAVITA INC",
      "ticker": "DVA",
      "title_of_class": "COM",
      "value": 2324865095,
      "shares": 15126977,
      "share_type": "SH",
      "put_call": null,
      "sector": null
    },
    {
      "cusip": "247361702",
      "name": "DELTA AIR LINES INC",
      "ticker": "DAL",
      "title_of_class": "COM NEW",
      "value": 2646532635,
      "shares": 39809456,
      "share_type": "SH",
      "put_call": null,
      "sector": null
    },
    {
      "cusip": "47233W109",
      "name": "JEFFERIES FINANCIAL GROUP IN",
      "ticker": "JEF",
      "title_of_class": "COM",
      "value": 17892939,
      "shares": 433558,
      "share_type": "SH",
      "put_call": null,
      "sector": null
    },
    {
      "cusip": "500754106",
      "name": "KRAFT HEINZ CO",
      "ticker": "KHC",
      "title_of_class": "COM",
      "value": 7323527057,
      "shares": 325634818,
      "share_type": "SH",
      "put_call": null,
      "sector": null
    },
    {
      "cusip": "501044101",
      "name": "KROGER CO",
      "ticker": "KR",
      "title_of_class": "COM",
      "value": 1165509032,
      "shares": 16107090,
      "share_type": "SH",
      "put_call": null,
      "sector": null
    },
    {
      "cusip": "501044101",
      "name": "KROGER CO",
      "ticker": "KR",
      "title_of_class": "COM",
      "value": 55610903,
      "shares": 768531,
      "share_type": "SH",
      "put_call": null,
      "sector": null
    },
    {
      "cusip": "501044101",
      "name": "KROGER CO",
      "ticker": "KR",
      "title_of_class": "COM",
      "value": 388364731,
      "shares": 5367119,
      "share_type": "SH",
      "put_call": null,
      "sector": null
    },
    {
      "cusip": "501044101",
      "name": "KROGER CO",
      "ticker": "KR",
      "title_of_class": "COM",
      "value": 36180000,
      "shares": 500000,
      "share_type": "SH",
      "put_call": null,
      "sector": null
    },
    {
      "cusip": "501044101",
      "name": "KROGER CO",
      "ticker": "KR",
      "title_of_class": "COM",
      "value": 1972335334,
      "shares": 27257260,
      "share_type": "SH",
      "put_call": null,
      "sector": null
    },
    {
      "cusip": "526057104",
      "name": "LENNAR CORP",
      "ticker": "LEN-B",
      "title_of_class": "CL A",
      "value": 877052911,
      "shares": 10099642,
      "share_type": "SH",
      "put_call": null,
      "sector": null
    },
    {
      "cusip": "526057302",
      "name": "LENNAR CORP",
      "ticker": "LEN-B",
      "title_of_class": "CL B",
      "value": 19995576,
      "shares": 237703,
      "share_type": "SH",
      "put_call": null,
      "sector": null
    },
    {
      "cusip": "530909100",
      "name": "LIBERTY LIVE HOLDINGS INC",
      "ticker": "LLYVK",
      "title_of_class": "COM SER A",
      "value": 92712005,
      "shares": 1011698,
      "share_type": "SH",
      "put_call": null,
      "sector": null
    },
    {
      "cusip": "530909100",
      "name": "LIBERTY LIVE HOLDINGS INC",
      "ticker": "LLYVK",
      "title_of_class": "COM SER A",
      "value": 301016781,
      "shares": 3284775,
      "share_type": "SH",
      "put_call": null,
      "sector": null
    },
    {
      "cusip": "530909100",
      "name": "LIBERTY LIVE HOLDINGS INC",
      "ticker": "LLYVK",
      "title_of_class": "COM SER A",
      "value": 21383919,
      "shares": 233347,
      "share_type": "SH",
      "put_call": null,
      "sector": null
    },
    {
      "cusip": "530909100",
      "name": "LIBERTY LIVE HOLDINGS INC",
      "ticker": "LLYVK",
      "title_of_class": "COM SER A",
      "value": 41858220,
      "shares": 456768,
      "share_type": "SH",
      "put_call": null,
      "sector": null
    },
    {
      "cusip": "530909308",
      "name": "LIBERTY LIVE HOLDINGS INC",
      "ticker": "LLYVK",
      "title_of_class": "COM SHS SER C",
      "value": 327469956,
      "shares": 3479651,
      "share_type": "SH",
      "put_call": null,
      "sector": null
    },
    {
      "cusip": "530909308",
      "name": "LIBERTY LIVE HOLDINGS INC",
      "ticker": "LLYVK",
      "title_of_class": "COM SHS SER C",
      "value": 518318636,
      "shares": 5507583,
      "share_type": "SH",
      "put_call": null,
      "sector": null
    },
    {
      "cusip": "530909308",
      "name": "LIBERTY LIVE HOLDINGS INC",
      "ticker": "LLYVK",
      "title_of_class": "COM SHS SER C",
      "value": 15304168,
      "shares": 162620,
      "share_type": "SH",
      "put_call": null,
      "sector": null
    },
    {
      "cusip": "530909308",
      "name": "LIBERTY LIVE HOLDINGS INC",
      "ticker": "LLYVK",
      "title_of_class": "COM SHS SER C",
      "value": 135263268,
      "shares": 1437289,
      "share_type": "SH",
      "put_call": null,
      "sector": null
    },
    {
      "cusip": "546347105",
      "name": "LOUISIANA PAC CORP",
      "ticker": "LPX",
      "title_of_class": "COM",
      "value": 96021561,
      "shares": 1319884,
      "share_type": "SH",
      "put_call": null,
      "sector": null
    },
    {
      "cusip": "546347105",
      "name": "LOUISIANA PAC CORP",
      "ticker": "LPX",
      "title_of_class": "COM",
      "value": 316092130,
      "shares": 4344909,
      "share_type": "SH",
      "put_call": null,
      "sector": null
    },
    {
      "cusip": "55616P104",
      "name": "MACYS INC",
      "ticker": "M",
      "title_of_class": "COM",
      "value": 24895928,
      "shares": 1376226,
      "share_type": "SH",
      "put_call": null,
      "sector": null
    },
    {
      "cusip": "55616P104",
      "name": "MACYS INC",
      "ticker": "M",
      "title_of_class": "COM",
      "value": 30067914,
      "shares": 1662129,
      "share_type": "SH",
      "put_call": null,
      "sector": null
    },
    {
      "cusip": "615369105",
      "name": "MOODYS CORP",
      "ticker": "MCO",
      "title_of_class": "COM",
      "value": 31453625,
      "shares": 72100,
      "share_type": "SH",
      "put_call": null,
      "sector": null
    },
    {
      "cusip": "615369105",
      "name": "MOODYS CORP",
      "ticker": "MCO",
      "title_of_class": "COM",
      "value": 5223626090,
      "shares": 11973928,
      "share_type": "SH",
      "put_call": null,
      "sector": null
    },
    {
      "cusip": "615369105",
      "name": "MOODYS CORP",
      "ticker": "MCO",
      "title_of_class": "COM",
      "value": 5507110938,
      "shares": 12623750,
      "share_type": "SH",
      "put_call": null,
      "sector": null
    },
    {
      "cusip": "62944T105",
      "name": "NVR INC",
      "ticker": "NVR",
      "title_of_class": "COM",
      "value": 73226191,
      "shares": 11112,
      "share_type": "SH",
      "put_call": null,
      "sector": null
    },
    {
      "cusip": "650111107",
      "name": "NEW YORK TIMES CO MTN BE",
      "ticker": "NYT",
      "title_of_class": "CL A",
      "value": 117222000,
      "shares": 1400000,
      "share_type": "SH",
      "put_call": null,
      "sector": null
    },
    {
      "cusip": "650111107",
      "name": "NEW YORK TIMES CO MTN BE",
      "ticker": "NYT",
      "title_of_class": "CL A",
      "value": 1150997376,
      "shares": 13746535,
      "share_type": "SH",
      "put_call": null,
      "sector": null
    },
    {
      "cusip": "670346105",
      "name": "NUCOR CORP",
      "ticker": "NUE",
      "title_of_class": "COM",
      "value": 660686383,
      "shares": 3907075,
      "share_type": "SH",
      "put_call": null,
      "sector": null
    },
    {
      "cusip": "674599105",
      "name": "OCCIDENTAL PETE CORP",
      "ticker": "OXY-WT",
      "title_of_class": "COM",
      "value": 17221193015,
      "shares": 264941431,
      "share_type": "SH",
      "put_call": null,
      "sector": null
    },
    {
      "cusip": "829933100",
      "name": "SIRIUSXM HOLDINGS INC",
      "ticker": "SIRI",
      "title_of_class": "COMMON STOCK",
      "value": 368931261,
      "shares": 15984890,
      "share_type": "SH",
      "put_call": null,
      "sector": null
    },
    {
      "cusip": "829933100",
      "name": "SIRIUSXM HOLDINGS INC",
      "ticker": "SIRI",
      "title_of_class": "COMMON STOCK",
      "value": 2511616999,
      "shares": 108822227,
      "share_type": "SH",
      "put_call": null,
      "sector": null
    },
    {
      "cusip": "92343E102",
      "name": "VERISIGN INC",
      "ticker": "VRSN",
      "title_of_class": "COM",
      "value": 241641117,
      "shares": 972947,
      "share_type": "SH",
      "put_call": null,
      "sector": null
    },
    {
      "cusip": "92343E102",
      "name": "VERISIGN INC",
      "ticker": "VRSN",
      "title_of_class": "COM",
      "value": 1991085480,
      "shares": 8016933,
      "share_type": "SH",
      "put_call": null,
      "sector": null
    },
    {
      "cusip": "H1467J104",
      "name": "CHUBB LTD SWITZ",
      "ticker": "CB",
      "title_of_class": "COM",
      "value": 11162836215,
      "shares": 34249183,
      "share_type": "SH",
      "put_call": null,
      "sector": null
    }
  ]
}